fastapi_autoloader/__init__.py
fastapi_autoloader/autoloader.py
fastapi_autoloader-0.1.4.dist-info/METADATA
fastapi_autoloader-0.1.4.dist-info/WHEEL
fastapi_autoloader-0.1.4.dist-info/RECORD
