Metadata-Version: 2.3
Name: fastapi-autoloader
Version: 0.1.4
Summary: MVC style router autoload
License: MIT
Keywords: fastapi,autoloader,dynamic-router,mvc,router,autoload
Author: Juan Borda
Author-email: juanignacioborda@gmail.com
Requires-Python: >=3.9,<4.0
Classifier: License :: OSI Approved :: MIT License
Classifier: Programming Language :: Python :: 3
Classifier: Programming Language :: Python :: 3.9
Classifier: Programming Language :: Python :: 3.10
Classifier: Programming Language :: Python :: 3.11
Classifier: Programming Language :: Python :: 3.12
Classifier: Programming Language :: Python :: 3.13
Requires-Dist: fastapi (>=0.110.0)
Project-URL: Repository, https://github.com/juanitomint/fastapi-autoloader.git
